{
	"type": "passwordscene",
	"entities": {
		"ResponsiveLayout": {
			"rows": {
				"1": {
					"Entity": {
						"weidth": 100,
						"height": 5
					}
				},
				"2": {
					"TextEntity": {
						"width": 100,
						"min_width": 300,
						"min_height": "fonts.title",
						"font": "title",
						"i18ntext": "game.title",
						"shrink2fit": true
					}
				},
				"3": {
					"RectEntity": {
						"width": 80,
						"height": 60,
						"min_height": "fonts.small",
						"color": "textbox",
						"entities": {
							"TextEntity": {
								"font": "small",
								"textbox": true,
								"sceneHandle": "messenger",
								"margin": 5
							}
						}
					}
				}
			}
		}
	}
}